aina/__init__.py
aina/server.py
aina/web.py
aina/api/__init__.py
aina/api/api.py
aina/api/response.py
aina/db/__init__.py
aina/model/__init__.py
aina/model/call_qianfan.py
aina/model/cli_demo.py
aina/model/model.py
aina/model/msg.py
aina/rag/__init__.py
aina/tools/__init__.py
aina/tools/dealfile.py
reno_aina-0.1.0.dist-info/LICENSE
reno_aina-0.1.0.dist-info/METADATA
reno_aina-0.1.0.dist-info/WHEEL
reno_aina-0.1.0.dist-info/top_level.txt
reno_aina-0.1.0.dist-info/RECORD
