Metadata-Version: 2.1
Name: reno_aina
Version: 0.1.0
Summary: reno aina
Home-page: https://github.com/renoyuan/AinA
Author: renoyuan
Author-email: renoyuan@foxmail.com
Classifier: Programming Language :: Python :: 3
Classifier: License :: OSI Approved :: Apache Software License
Classifier: Operating System :: OS Independent
Requires-Python: >=3.11
License-File: LICENSE
Requires-Dist: fastapi >=0.111.1
Requires-Dist: loguru >=0.7.2
Requires-Dist: qianfan >=0.4.2
Requires-Dist: torch >=2.3.1
Requires-Dist: transformers >=4.42.4
Requires-Dist: gradio >=4.39.0
